ekonlpy/__cli__.py
ekonlpy/__init__.py
ekonlpy/_version.py
ekonlpy/py.typed
ekonlpy/base/__init__.py
ekonlpy/base/base.py
ekonlpy/data/__init__.py
ekonlpy/data/tagset.py
ekonlpy/data/dictionary/ADJECTIVES.txt
ekonlpy/data/dictionary/ADVERBS.txt
ekonlpy/data/dictionary/COUNTRY.txt
ekonlpy/data/dictionary/CURRENCY.txt
ekonlpy/data/dictionary/ECON_PHRASES.txt
ekonlpy/data/dictionary/ECON_TERMS.txt
ekonlpy/data/dictionary/ENTITY.txt
ekonlpy/data/dictionary/FOREIGN_TERMS.txt
ekonlpy/data/dictionary/GENERIC.txt
ekonlpy/data/dictionary/INDUSTRY_TERMS.txt
ekonlpy/data/dictionary/INSTITUTION.txt
ekonlpy/data/dictionary/LEMMA.txt
ekonlpy/data/dictionary/NAMES.txt
ekonlpy/data/dictionary/NOUNS.txt
ekonlpy/data/dictionary/POLARITY_PHRASES.txt
ekonlpy/data/dictionary/PROPER_NOUNS.txt
ekonlpy/data/dictionary/SECTOR.txt
ekonlpy/data/dictionary/STOPWORDS.txt
ekonlpy/data/dictionary/STOPWORDS_CUST.txt
ekonlpy/data/dictionary/STOPWORDS_EN.txt
ekonlpy/data/dictionary/STOPWORDS_KOR.txt
ekonlpy/data/dictionary/SYNONYM.txt
ekonlpy/data/dictionary/SYNONYM_MAG.txt
ekonlpy/data/dictionary/SYNONYM_PHRASES.txt
ekonlpy/data/dictionary/SYNONYM_TERMS.txt
ekonlpy/data/dictionary/SYNONYM_VA.txt
ekonlpy/data/dictionary/UNIT.txt
ekonlpy/data/dictionary/VERBS.txt
ekonlpy/data/lexicon/Currencies.txt
ekonlpy/data/lexicon/DatesandNumbers.txt
ekonlpy/data/lexicon/Generic.txt
ekonlpy/data/lexicon/Geographic.txt
ekonlpy/data/lexicon/HIV-4.csv
ekonlpy/data/lexicon/LM.csv
ekonlpy/data/lexicon/Names.txt
ekonlpy/data/lexicon/euko/mp_uncertainty_lexicon_lex.csv
ekonlpy/data/lexicon/euko/mp_uncertainty_lexicon_mkt.csv
ekonlpy/data/lexicon/kosac/expressive-type.csv
ekonlpy/data/lexicon/kosac/intensity.csv
ekonlpy/data/lexicon/kosac/polarity.csv
ekonlpy/data/lexicon/mpko/mp_polarity_lexicon_lex.csv
ekonlpy/data/lexicon/mpko/mp_polarity_lexicon_mkt.csv
ekonlpy/data/lexicon/mpko/mp_polarity_lexicon_mkt_n3.csv
ekonlpy/data/lexicon/mpko/mp_polarity_lexicon_mkt_n7.csv
ekonlpy/data/lexicon/mpko/mp_polarity_vocab.txt
ekonlpy-2.2.0.dist-info/METADATA
ekonlpy-2.2.0.dist-info/WHEEL
ekonlpy-2.2.0.dist-info/entry_points.txt
ekonlpy-2.2.0.dist-info/licenses/LICENSE
ekonlpy-2.2.0.dist-info/RECORD
