Metadata-Version: 2.4
Name: eKoNLPy
Version: 2.2.0
Summary: A Korean natural language processing toolkit for economic analysis
Project-URL: Homepage, https://ekonlpy.entelecheia.ai
Project-URL: Repository, https://github.com/entelecheia/eKoNLPy
Project-URL: Documentation, https://ekonlpy.entelecheia.ai
Author-email: Young Joon Lee <entelecheia@hotmail.com>
License-Expression: MIT
License-File: LICENSE
Keywords: KoNLPy,Monetary policy,Sentiment analysis,Tokenization
Classifier: Intended Audience :: Developers
Classifier: Programming Language :: Python
Classifier: Programming Language :: Python :: 3
Classifier: Programming Language :: Python :: 3.9
Classifier: Programming Language :: Python :: 3.10
Classifier: Programming Language :: Python :: 3.11
Classifier: Programming Language :: Python :: 3.12
Classifier: Programming Language :: Python :: 3.13
Classifier: Topic :: Software Development :: Libraries :: Python Modules
Requires-Python: <4.0,>=3.9
Requires-Dist: click>=8.1.6
Requires-Dist: fugashi>=1.3.3
Requires-Dist: mecab-ko-dic>=1.0.0
Requires-Dist: nltk>=3.8.1
Requires-Dist: pandas<=2.3.2,>=1.5.3
Requires-Dist: scipy<=1.13.1,>1.10.0
